dirtree/__init__.py
dirtree/main.py
llmdirtree-0.1.5.dist-info/METADATA
llmdirtree-0.1.5.dist-info/WHEEL
llmdirtree-0.1.5.dist-info/entry_points.txt
llmdirtree-0.1.5.dist-info/top_level.txt
llmdirtree-0.1.5.dist-info/RECORD
