Metadata-Version: 2.2
Name: llmdirtree
Version: 0.1.5
Summary: A simple directory tree generator for llm
Home-page: https://github.com/arun477/dirtree
Author: arun
Author-email: your.email@example.com
Classifier: Programming Language :: Python :: 3
Classifier: License :: OSI Approved :: MIT License
Classifier: Operating System :: OS Independent
Requires-Python: >=3.6
Provides-Extra: progress
Requires-Dist: tqdm; extra == "progress"
Dynamic: author
Dynamic: author-email
Dynamic: classifier
Dynamic: description
Dynamic: description-content-type
Dynamic: home-page
Dynamic: provides-extra
Dynamic: requires-python
Dynamic: summary
